pulp_gem/__init__.py
pulp_gem/pytest_plugin.py
pulp_gem/specs.py
pulp_gem/app/__init__.py
pulp_gem/app/models.py
pulp_gem/app/replica.py
pulp_gem/app/serializers.py
pulp_gem/app/settings.py
pulp_gem/app/viewsets.py
pulp_gem/app/migrations/0001_initial.py
pulp_gem/app/migrations/0001_initial_squashed_0011_alter_gemcontent_platform.py
pulp_gem/app/migrations/0002_gemrepository.py
pulp_gem/app/migrations/0003_move_data_to_new_master_distribution_model.py
pulp_gem/app/migrations/0004_alter_gemcontent_content_ptr_and_more.py
pulp_gem/app/migrations/0005_rename_gemcontent_shallowgemcontent.py
pulp_gem/app/migrations/0006_gemremote_excludes_gemremote_includes_and_more.py
pulp_gem/app/migrations/0007_DATA_fix_prerelease.py
pulp_gem/app/migrations/0008_gemcontent_platform.py
pulp_gem/app/migrations/0009_check_datarepair.py
pulp_gem/app/migrations/0010_delete_shallowgemcontent.py
pulp_gem/app/migrations/0011_alter_gemcontent_platform.py
pulp_gem/app/migrations/0012_alter_gemdistribution_options_and_more.py
pulp_gem/app/migrations/__init__.py
pulp_gem/app/tasks/__init__.py
pulp_gem/app/tasks/publishing.py
pulp_gem/app/tasks/synchronizing.py
pulp_gem/tests/__init__.py
pulp_gem/tests/functional/__init__.py
pulp_gem/tests/functional/constants.py
pulp_gem/tests/functional/api/__init__.py
pulp_gem/tests/functional/api/test_crud_content_unit.py
pulp_gem/tests/functional/api/test_crud_remotes.py
pulp_gem/tests/functional/api/test_domain.py
pulp_gem/tests/functional/api/test_download_content.py
pulp_gem/tests/functional/api/test_publish.py
pulp_gem/tests/functional/api/test_pull_through.py
pulp_gem/tests/functional/api/test_replicate.py
pulp_gem/tests/functional/api/test_sync.py
pulp_gem/tests/unit/__init__.py
pulp_gem/tests/unit/test_serializers.py
pulp_gem/tests/unit/test_spec.py
pulp_gem-0.7.5.dist-info/licenses/LICENSE
pulp_gem-0.7.5.dist-info/METADATA
pulp_gem-0.7.5.dist-info/WHEEL
pulp_gem-0.7.5.dist-info/entry_points.txt
pulp_gem-0.7.5.dist-info/top_level.txt
pulp_gem-0.7.5.dist-info/RECORD
