Metadata-Version: 2.4
Name: pulp-gem
Version: 0.7.5
Summary: Gemfile plugin for the Pulp Project
Author-email: Pulp Team <pulp-list@redhat.com>
Project-URL: Homepage, https://pulpproject.org
Project-URL: Documentation, https://pulpproject.org/pulp_gem/
Project-URL: Repository, https://github.com/pulp/pulp_gem
Project-URL: Bug Tracker, https://github.com/pulp/pulp_gem/issues
Project-URL: Changelog, https://pulpproject.org/pulp_gem/changes/
Classifier: License :: OSI Approved :: GNU General Public License v2 or later (GPLv2+)
Classifier: Operating System :: POSIX :: Linux
Classifier: Development Status :: 5 - Production/Stable
Classifier: Framework :: Django
Classifier: Programming Language :: Python
Classifier: Programming Language :: Python :: 3
Requires-Python: >=3.9
License-File: LICENSE
Requires-Dist: pulpcore<3.115,>=3.49.0
Requires-Dist: pulp_glue_gem<0.6,>=0.3.0
Requires-Dist: rubymarshal<1.3,>=1.2.7
Dynamic: license-file
